[
  {
    "id": "P7-001",
    "code": "P7-001 P760201 [CSIE7096]",
    "name": "專題討論 資工所/醫資所/多媒體學位學程/AI學位學程合班,大學部勿選",
    "grade": 1,
    "credits": 0,
    "required": true,
    "college": "電機資訊學院",
    "departmentCode": "P7",
    "department": "資訊所 CSIE",
    "teacher": "王士豪",
    "enrollment": "434/不5限",
    "locations": [
      "A1302",
      "共同教室"
    ],
    "period": "[5]6~7 共同教室 A1302",
    "slots": [
      {
        "day": 5,
        "period": "6",
        "type": "研討"
      },
      {
        "day": 5,
        "period": "7",
        "type": "研討"
      }
    ]
  },
  {
    "id": "P7-003",
    "code": "P7-003 P75F300 [CSIE7095]",
    "name": "資工與醫資導論 須修過本課方可畢業，資工所/醫資所/AI學位學程合班",
    "grade": 1,
    "credits": 1,
    "required": false,
    "college": "電機資訊學院",
    "departmentCode": "P7",
    "department": "資訊所 CSIE",
    "teacher": "王士豪",
    "enrollment": "239/60",
    "locations": [
      "A1302",
      "共同教室"
    ],
    "period": "[5]5 共同教室 A1302",
    "slots": [
      {
        "day": 5,
        "period": "5",
        "type": "講義"
      }
    ]
  },
  {
    "id": "P7-006",
    "code": "P7-006 P76A200 [CSIE7119]",
    "name": "普及運算專論 資工所/醫資所/AI學位學程合班",
    "grade": 1,
    "credits": 3,
    "required": false,
    "college": "電機資訊學院",
    "departmentCode": "P7",
    "department": "資訊所 CSIE",
    "teacher": "郭耀煌",
    "enrollment": "54/51",
    "locations": [
      "65105",
      "資訊新館"
    ],
    "period": "[1]2~4 資訊新館 65105",
    "slots": [
      {
        "day": 1,
        "period": "2",
        "type": "講義"
      },
      {
        "day": 1,
        "period": "3",
        "type": "講義"
      },
      {
        "day": 1,
        "period": "4",
        "type": "講義"
      }
    ]
  },
  {
    "id": "P7-007",
    "code": "P7-007 P772800 [CSIE7621]",
    "name": "下世代無線行動網路 英語授課  資工所/醫資所/AI學位學程/製造所合班,英語授課",
    "grade": 1,
    "credits": 3,
    "required": false,
    "college": "電機資訊學院",
    "departmentCode": "P7",
    "department": "資訊所 CSIE",
    "teacher": "黃崇明",
    "enrollment": "7/553",
    "locations": [
      "資訊系館",
      "4201"
    ],
    "period": "[4]6~8 資訊系館 4201",
    "slots": [
      {
        "day": 4,
        "period": "6",
        "type": "講義"
      },
      {
        "day": 4,
        "period": "7",
        "type": "講義"
      },
      {
        "day": 4,
        "period": "8",
        "type": "講義"
      }
    ]
  },
  {
    "id": "P7-008",
    "code": "P7-008 P762800 [CSIE7108]",
    "name": "電腦繪圖 資工所/AI學位學程合班，大學部勿選",
    "grade": 1,
    "credits": 3,
    "required": false,
    "college": "電機資訊學院",
    "departmentCode": "P7",
    "department": "資訊所 CSIE",
    "teacher": "李同益",
    "enrollment": "24/36",
    "locations": [
      "4261",
      "資訊系館"
    ],
    "period": "[1]6~7 資訊系館 4261 [3]7 資訊系館 4261",
    "slots": [
      {
        "day": 1,
        "period": "6",
        "type": "講義"
      },
      {
        "day": 1,
        "period": "7",
        "type": "講義"
      },
      {
        "day": 3,
        "period": "7",
        "type": "講義"
      }
    ]
  },
  {
    "id": "P7-009",
    "code": "P7-009 P75H400 [CSIE7102]",
    "name": "節能光網路專論 資工所/AI學位學程合班",
    "grade": 1,
    "credits": 3,
    "required": false,
    "college": "電機資訊學院",
    "departmentCode": "P7",
    "department": "資訊所 CSIE",
    "teacher": "蘇銓清",
    "enrollment": "8/552",
    "locations": [
      "資訊系館",
      "4202"
    ],
    "period": "[4]6~8 資訊系館 4202",
    "slots": [
      {
        "day": 4,
        "period": "6",
        "type": "講義"
      },
      {
        "day": 4,
        "period": "7",
        "type": "講義"
      },
      {
        "day": 4,
        "period": "8",
        "type": "講義"
      }
    ]
  },
  {
    "id": "P7-010",
    "code": "P7-010 P75H600 [CSIE7104]",
    "name": "智慧感測與行動計算 人工智慧學分學程 遠距課程  資工所/醫資所/AI學位學程合班，遠距課程",
    "grade": 1,
    "credits": 3,
    "required": false,
    "college": "電機資訊學院",
    "departmentCode": "P7",
    "department": "資訊所 CSIE",
    "teacher": "鄭憲宗",
    "enrollment": "12/額滿",
    "locations": [],
    "period": "[2]N~6",
    "slots": [
      {
        "day": 2,
        "period": "N",
        "type": "講義"
      },
      {
        "day": 2,
        "period": "5",
        "type": "講義"
      },
      {
        "day": 2,
        "period": "6",
        "type": "講義"
      }
    ]
  },
  {
    "id": "P7-013",
    "code": "P7-013 P753900 [CSIE7008]",
    "name": "數位信號處理 人工智慧學分學程  資工所/醫資所/AI學位學程/製造所/智慧製造學程合班",
    "grade": 1,
    "credits": 3,
    "required": false,
    "college": "電機資訊學院",
    "departmentCode": "P7",
    "department": "資訊所 CSIE",
    "teacher": "吳宗憲",
    "enrollment": "46/額5滿",
    "locations": [
      "65104",
      "資訊新館"
    ],
    "period": "[1]6~8 資訊新館 65104",
    "slots": [
      {
        "day": 1,
        "period": "6",
        "type": "講義"
      },
      {
        "day": 1,
        "period": "7",
        "type": "講義"
      },
      {
        "day": 1,
        "period": "8",
        "type": "講義"
      }
    ]
  },
  {
    "id": "P7-014",
    "code": "P7-014 P76C700 [CSIE7129]",
    "name": "口語感知及互動專論 資工所/AI學位學程/智慧製造學程合班",
    "grade": 1,
    "credits": 3,
    "required": false,
    "college": "電機資訊學院",
    "departmentCode": "P7",
    "department": "資訊所 CSIE",
    "teacher": "吳宗憲",
    "enrollment": "55/5",
    "locations": [
      "65805",
      "資訊新館"
    ],
    "period": "[2]2~4 資訊新館 65805",
    "slots": [
      {
        "day": 2,
        "period": "2",
        "type": "講義"
      },
      {
        "day": 2,
        "period": "3",
        "type": "講義"
      },
      {
        "day": 2,
        "period": "4",
        "type": "講義"
      }
    ]
  },
  {
    "id": "P7-015",
    "code": "P7-015 P75A500 [CSIE7020]",
    "name": "生醫資訊擷取技術 人工智慧學分學程  資工所/醫資所/AI學位學程合班",
    "grade": 1,
    "credits": 3,
    "required": false,
    "college": "電機資訊學院",
    "departmentCode": "P7",
    "department": "資訊所 CSIE",
    "teacher": "蔣榮先",
    "enrollment": "4/517",
    "locations": [
      "65605",
      "資訊新館"
    ],
    "period": "[2]2~4 資訊新館 65605",
    "slots": [
      {
        "day": 2,
        "period": "2",
        "type": "講義"
      },
      {
        "day": 2,
        "period": "3",
        "type": "講義"
      },
      {
        "day": 2,
        "period": "4",
        "type": "講義"
      }
    ]
  },
  {
    "id": "P7-016",
    "code": "P7-016 P76I200 [CSIE7606]",
    "name": "電腦視覺與深度學習 人工智慧學分學程 英語授課  資工所/醫資所/AI學位學程/製造所/運算學院/數據所合班，英語授課。",
    "grade": 1,
    "credits": 3,
    "required": false,
    "college": "電機資訊學院",
    "departmentCode": "P7",
    "department": "資訊所 CSIE",
    "teacher": "連震杰",
    "enrollment": "239/60",
    "locations": [
      "A1302",
      "共同教室"
    ],
    "period": "[5]2~4 共同教室 A1302",
    "slots": [
      {
        "day": 5,
        "period": "2",
        "type": "講義"
      },
      {
        "day": 5,
        "period": "3",
        "type": "講義"
      },
      {
        "day": 5,
        "period": "4",
        "type": "講義"
      }
    ]
  },
  {
    "id": "P7-018",
    "code": "P7-018 P754600 [CSIE7010]",
    "name": "圖形理論 資訊所/醫資所/AI學位學程/製造所合班",
    "grade": 1,
    "credits": 3,
    "required": false,
    "college": "電機資訊學院",
    "departmentCode": "P7",
    "department": "資訊所 CSIE",
    "teacher": "謝孫源",
    "enrollment": "115/15",
    "locations": [
      "資訊系館",
      "4264"
    ],
    "period": "[2]2~4 資訊系館 4264",
    "slots": [
      {
        "day": 2,
        "period": "2",
        "type": "講義"
      },
      {
        "day": 2,
        "period": "3",
        "type": "講義"
      },
      {
        "day": 2,
        "period": "4",
        "type": "講義"
      }
    ]
  },
  {
    "id": "P7-020",
    "code": "P7-020 P752500 [CSIE7005]",
    "name": "網路資源開發暨利用 資訊所/醫資所/AI學位學程合班",
    "grade": 1,
    "credits": 3,
    "required": false,
    "college": "電機資訊學院",
    "departmentCode": "P7",
    "department": "資訊所 CSIE",
    "teacher": "盧文祥",
    "enrollment": "5/510",
    "locations": [
      "4210A",
      "資訊系館"
    ],
    "period": "[4]6~8 資訊系館 4210A",
    "slots": [
      {
        "day": 4,
        "period": "6",
        "type": "講義"
      },
      {
        "day": 4,
        "period": "7",
        "type": "講義"
      },
      {
        "day": 4,
        "period": "8",
        "type": "講義"
      }
    ]
  },
  {
    "id": "P7-024",
    "code": "P7-024 P773000 [CSIE7622]",
    "name": "光網路之深入探究",
    "grade": 1,
    "credits": 3,
    "required": false,
    "college": "電機資訊學院",
    "departmentCode": "P7",
    "department": "資訊所 CSIE",
    "teacher": "許靜芳",
    "enrollment": "3/52",
    "locations": [
      "65104",
      "資訊新館"
    ],
    "period": "[3]2 資訊新館 65104 [5]3~4 資訊新館 65104",
    "slots": [
      {
        "day": 3,
        "period": "2",
        "type": "講義"
      },
      {
        "day": 5,
        "period": "3",
        "type": "講義"
      },
      {
        "day": 5,
        "period": "4",
        "type": "講義"
      }
    ]
  },
  {
    "id": "P7-025",
    "code": "P7-025 P76G500 [CSIE7211]",
    "name": "計算機結構 英語授課  資工所/醫資所/AI學位學程/製造所合班,英語授課。增開第二間教室4202",
    "grade": 1,
    "credits": 3,
    "required": false,
    "college": "電機資訊學院",
    "departmentCode": "P7",
    "department": "資訊所 CSIE",
    "teacher": "黃敬群",
    "enrollment": "654/99",
    "locations": [
      "4203",
      "資訊系館"
    ],
    "period": "[2]2~4 資訊系館 4203",
    "slots": [
      {
        "day": 2,
        "period": "2",
        "type": "講義"
      },
      {
        "day": 2,
        "period": "3",
        "type": "講義"
      },
      {
        "day": 2,
        "period": "4",
        "type": "講義"
      }
    ]
  },
  {
    "id": "P7-026",
    "code": "P7-026 P75C600 [CSIE7030]",
    "name": "生醫訊號處理 資工所/醫資所/AI學位學程/製造所合班",
    "grade": 1,
    "credits": 3,
    "required": false,
    "college": "電機資訊學院",
    "departmentCode": "P7",
    "department": "資訊所 CSIE",
    "teacher": "梁勝富",
    "enrollment": "31/77",
    "locations": [
      "4204",
      "資訊系館"
    ],
    "period": "[2]2~4 資訊系館 4204",
    "slots": [
      {
        "day": 2,
        "period": "2",
        "type": "講義"
      },
      {
        "day": 2,
        "period": "3",
        "type": "講義"
      },
      {
        "day": 2,
        "period": "4",
        "type": "講義"
      }
    ]
  },
  {
    "id": "P7-031",
    "code": "P7-031 P75L900 [CSIE7651]",
    "name": "數位IC設計 人工智慧學分學程  資工所/AI學位學程合班",
    "grade": 1,
    "credits": 3,
    "required": false,
    "college": "電機資訊學院",
    "departmentCode": "P7",
    "department": "資訊所 CSIE",
    "teacher": "陳培殷*",
    "enrollment": "5111/額滿",
    "locations": [
      "資訊系館",
      "4264"
    ],
    "period": "[1]2~4 資訊系館 4264",
    "slots": [
      {
        "day": 1,
        "period": "2",
        "type": "講義"
      },
      {
        "day": 1,
        "period": "3",
        "type": "講義"
      },
      {
        "day": 1,
        "period": "4",
        "type": "講義"
      }
    ]
  },
  {
    "id": "P7-032",
    "code": "P7-032 P76D500 [CSIE7132]",
    "name": "網路入侵偵測系統設計專論 資工所/AI學位學程合班",
    "grade": 1,
    "credits": 3,
    "required": false,
    "college": "電機資訊學院",
    "departmentCode": "P7",
    "department": "資訊所 CSIE",
    "teacher": "張燕光",
    "enrollment": "75/48",
    "locations": [
      "65105",
      "資訊新館"
    ],
    "period": "[3]2~4 資訊新館 65105",
    "slots": [
      {
        "day": 3,
        "period": "2",
        "type": "講義"
      },
      {
        "day": 3,
        "period": "3",
        "type": "講義"
      },
      {
        "day": 3,
        "period": "4",
        "type": "講義"
      }
    ]
  },
  {
    "id": "P7-033",
    "code": "P7-033 P755000 [CSIE7012]",
    "name": "影像處理 醫療器材與系統學程，人工智慧學分學程  資工所/醫資所/AI學位學程/製造所合班",
    "grade": 1,
    "credits": 3,
    "required": false,
    "college": "電機資訊學院",
    "departmentCode": "P7",
    "department": "資訊所 CSIE",
    "teacher": "洪昌鈺",
    "enrollment": "83/25",
    "locations": [
      "65405",
      "資訊新館"
    ],
    "period": "[4]6~8 資訊新館 65405",
    "slots": [
      {
        "day": 4,
        "period": "6",
        "type": "講義"
      },
      {
        "day": 4,
        "period": "7",
        "type": "講義"
      },
      {
        "day": 4,
        "period": "8",
        "type": "講義"
      }
    ]
  },
  {
    "id": "P7-034",
    "code": "P7-034 P76I600 [CSIE7617]",
    "name": "深度學習 人工智慧學分學程  資工所/醫資所/AI學位學程/製造所合班",
    "grade": 1,
    "credits": 3,
    "required": false,
    "college": "電機資訊學院",
    "departmentCode": "P7",
    "department": "資訊所 CSIE",
    "teacher": "洪昌鈺",
    "enrollment": "815/27",
    "locations": [
      "資訊系館",
      "4264"
    ],
    "period": "[2]6~8 資訊系館 4264",
    "slots": [
      {
        "day": 2,
        "period": "6",
        "type": "講義"
      },
      {
        "day": 2,
        "period": "7",
        "type": "講義"
      },
      {
        "day": 2,
        "period": "8",
        "type": "講義"
      }
    ]
  },
  {
    "id": "P7-035",
    "code": "P7-035 P76G100 [CSIE7150]",
    "name": "物聯網系統設計與應用 人工智慧學分學程  資工所/醫資所/AI學位學程/製造所合班",
    "grade": 1,
    "credits": 3,
    "required": false,
    "college": "電機資訊學院",
    "departmentCode": "P7",
    "department": "資訊所 CSIE",
    "teacher": "楊中平",
    "enrollment": "34/52",
    "locations": [
      "4261",
      "資訊系館"
    ],
    "period": "[4]2~4 資訊系館 4261",
    "slots": [
      {
        "day": 4,
        "period": "2",
        "type": "講義"
      },
      {
        "day": 4,
        "period": "3",
        "type": "講義"
      },
      {
        "day": 4,
        "period": "4",
        "type": "講義"
      }
    ]
  },
  {
    "id": "P7-036",
    "code": "P7-036 P774000 [CSIE7632]",
    "name": "深入emacs lisp 資工所/醫資所/AI學位學程/製造所合班",
    "grade": 1,
    "credits": 3,
    "required": false,
    "college": "電機資訊學院",
    "departmentCode": "P7",
    "department": "資訊所 CSIE",
    "teacher": "賀保羅",
    "enrollment": "8/52",
    "locations": [
      "資訊系館",
      "4201"
    ],
    "period": "[2]7~9 資訊系館 4201",
    "slots": [
      {
        "day": 2,
        "period": "7",
        "type": "講義"
      },
      {
        "day": 2,
        "period": "8",
        "type": "講義"
      },
      {
        "day": 2,
        "period": "9",
        "type": "講義"
      }
    ]
  },
  {
    "id": "P7-037",
    "code": "P7-037 P75L500 [CSIE7646]",
    "name": "基因體資訊學 資工所/醫資所/AI學位學程/製造所合班",
    "grade": 1,
    "credits": 3,
    "required": false,
    "college": "電機資訊學院",
    "departmentCode": "P7",
    "department": "資訊所 CSIE",
    "teacher": "賀保羅",
    "enrollment": "9/51",
    "locations": [
      "資訊系館",
      "4201"
    ],
    "period": "[4]2~4 資訊系館 4201",
    "slots": [
      {
        "day": 4,
        "period": "2",
        "type": "講義"
      },
      {
        "day": 4,
        "period": "3",
        "type": "講義"
      },
      {
        "day": 4,
        "period": "4",
        "type": "講義"
      }
    ]
  },
  {
    "id": "P7-038",
    "code": "P7-038 Q550400 [IMI7203]",
    "name": "醫用磁振造影：原理與應用 資工所/醫資所/AI學位學程/製造所合班",
    "grade": 1,
    "credits": 3,
    "required": false,
    "college": "電機資訊學院",
    "departmentCode": "P7",
    "department": "資訊所 CSIE",
    "teacher": "吳明龍",
    "enrollment": "5/25",
    "locations": [
      "4261",
      "資訊系館"
    ],
    "period": "[2]6~8 資訊系館 4261",
    "slots": [
      {
        "day": 2,
        "period": "6",
        "type": "講義"
      },
      {
        "day": 2,
        "period": "7",
        "type": "講義"
      },
      {
        "day": 2,
        "period": "8",
        "type": "講義"
      }
    ]
  },
  {
    "id": "P7-040",
    "code": "P7-040 P76E900 [CSIE7207]",
    "name": "空間資料分析專論 資工所/醫資所/AI學位學程合班",
    "grade": 1,
    "credits": 3,
    "required": false,
    "college": "電機資訊學院",
    "departmentCode": "P7",
    "department": "資訊所 CSIE",
    "teacher": "莊坤達",
    "enrollment": "57/53",
    "locations": [
      "4261",
      "資訊系館"
    ],
    "period": "[3]2~4 資訊系館 4261",
    "slots": [
      {
        "day": 3,
        "period": "2",
        "type": "講義"
      },
      {
        "day": 3,
        "period": "3",
        "type": "講義"
      },
      {
        "day": 3,
        "period": "4",
        "type": "講義"
      }
    ]
  },
  {
    "id": "P7-043",
    "code": "P7-043 P774100 [CSIE7633]",
    "name": "資訊科技產業專案設計 資工所/醫資所/AI學位學程/製造所合班。增開第二間教室4202",
    "grade": 1,
    "credits": 3,
    "required": false,
    "college": "電機資訊學院",
    "departmentCode": "P7",
    "department": "資訊所 CSIE",
    "teacher": "黃敬群",
    "enrollment": "1516/49",
    "locations": [
      "65405",
      "資訊新館"
    ],
    "period": "[2]7~9 資訊新館 65405",
    "slots": [
      {
        "day": 2,
        "period": "7",
        "type": "講義"
      },
      {
        "day": 2,
        "period": "8",
        "type": "講義"
      },
      {
        "day": 2,
        "period": "9",
        "type": "講義"
      }
    ]
  },
  {
    "id": "P7-044",
    "code": "P7-044 P76F500 [CSIE7144]",
    "name": "軟體設計 資工所/醫資所/AI學位學程/製造所合班",
    "grade": 1,
    "credits": 3,
    "required": false,
    "college": "電機資訊學院",
    "departmentCode": "P7",
    "department": "資訊所 CSIE",
    "teacher": "李信杰",
    "enrollment": "135/額滿",
    "locations": [
      "65405",
      "資訊新館"
    ],
    "period": "[3]2~4 資訊新館 65405",
    "slots": [
      {
        "day": 3,
        "period": "2",
        "type": "講義"
      },
      {
        "day": 3,
        "period": "3",
        "type": "講義"
      },
      {
        "day": 3,
        "period": "4",
        "type": "講義"
      }
    ]
  },
  {
    "id": "P7-046",
    "code": "P7-046 P773900 [CSIE7631]",
    "name": "物聯網技術之應用及系統開發 人工智慧學分學程  資工所/醫資所/AI學位學程/製造所合班",
    "grade": 1,
    "credits": 3,
    "required": false,
    "college": "電機資訊學院",
    "departmentCode": "P7",
    "department": "資訊所 CSIE",
    "teacher": "藍崑展",
    "enrollment": "14/46",
    "locations": [
      "65105",
      "資訊新館"
    ],
    "period": "[1]6~8 資訊新館 65105",
    "slots": [
      {
        "day": 1,
        "period": "6",
        "type": "講義"
      },
      {
        "day": 1,
        "period": "7",
        "type": "講義"
      },
      {
        "day": 1,
        "period": "8",
        "type": "講義"
      }
    ]
  },
  {
    "id": "P7-048",
    "code": "P7-048 P75L400 [CSIE7645]",
    "name": "人工智慧於醫療應用與服務 人工智慧學分學程  資訊所/醫資所/AI學位學程合班",
    "grade": 1,
    "credits": 3,
    "required": false,
    "college": "電機資訊學院",
    "departmentCode": "P7",
    "department": "資訊所 CSIE",
    "teacher": "王士豪* 蔡依珊",
    "enrollment": "41/51",
    "locations": [
      "4204",
      "資訊系館"
    ],
    "period": "[2]7~9 資訊系館 4204",
    "slots": [
      {
        "day": 2,
        "period": "7",
        "type": "講義"
      },
      {
        "day": 2,
        "period": "8",
        "type": "講義"
      },
      {
        "day": 2,
        "period": "9",
        "type": "講義"
      }
    ]
  },
  {
    "id": "P7-067",
    "code": "P7-067 P953100 [IMIS7219]",
    "name": "C#程式設計 製造所、資訊所、半導體學院合班",
    "grade": 1,
    "credits": 3,
    "required": false,
    "college": "電機資訊學院",
    "departmentCode": "P7",
    "department": "資訊所 CSIE",
    "teacher": "陳響亮",
    "enrollment": "34/18",
    "locations": [
      "資訊大樓",
      "75201"
    ],
    "period": "[2]6~8 資訊大樓 75201",
    "slots": [
      {
        "day": 2,
        "period": "6",
        "type": "講義"
      },
      {
        "day": 2,
        "period": "7",
        "type": "講義"
      },
      {
        "day": 2,
        "period": "8",
        "type": "講義"
      }
    ]
  },
  {
    "id": "P7-068",
    "code": "P7-068 P980500 [IMIS7236]",
    "name": "智慧加工系統 業界專家參與  製造所、資訊所、智慧製造學位學程、半導體學院合班",
    "grade": 1,
    "credits": 3,
    "required": false,
    "college": "電機資訊學院",
    "departmentCode": "P7",
    "department": "資訊所 CSIE",
    "teacher": "陳響亮",
    "enrollment": "21/4",
    "locations": [
      "照坤精密儀器大樓",
      "95519"
    ],
    "period": "[3]6~8 照坤精密儀器大樓 95519",
    "slots": [
      {
        "day": 3,
        "period": "6",
        "type": "講義"
      },
      {
        "day": 3,
        "period": "7",
        "type": "講義"
      },
      {
        "day": 3,
        "period": "8",
        "type": "講義"
      }
    ]
  },
  {
    "id": "P7-070",
    "code": "P7-070 P970900 [IMIS7215]",
    "name": "工業4.1:零缺陷的智慧製造 英語授課 智慧醫療專長微學程  製造所、資訊所、智慧製造學位學程、半導體學院、敏求學院合班，英語授課。",
    "grade": 1,
    "credits": 3,
    "required": false,
    "college": "電機資訊學院",
    "departmentCode": "P7",
    "department": "資訊所 CSIE",
    "teacher": "鄭芳田* 謝昱銘",
    "enrollment": "155/85",
    "locations": [
      "照坤精密儀器大樓",
      "95405"
    ],
    "period": "[5]B~D 照坤精密儀器大樓 95405",
    "slots": []
  },
  {
    "id": "P7-071",
    "code": "P7-071 P961900 [IMIS7241]",
    "name": "精實企業系統 製造所、資訊所、金融資訊產碩專班合班",
    "grade": 1,
    "credits": 3,
    "required": false,
    "college": "電機資訊學院",
    "departmentCode": "P7",
    "department": "資訊所 CSIE",
    "teacher": "楊大和",
    "enrollment": "153/12",
    "locations": [
      "照坤精密儀器大樓",
      "95405"
    ],
    "period": "[1]B~D 照坤精密儀器大樓 95405",
    "slots": []
  },
  {
    "id": "P7-072",
    "code": "P7-072 P980400 [IMIS7215]",
    "name": "資料驅動智慧型工業系統實務 製造所、資訊所、智慧製造學位學程合班",
    "grade": 1,
    "credits": 3,
    "required": false,
    "college": "電機資訊學院",
    "departmentCode": "P7",
    "department": "資訊所 CSIE",
    "teacher": "陳朝鈞",
    "enrollment": "16/4",
    "locations": [
      "照坤精密儀器大樓",
      "95519"
    ],
    "period": "[2]2~4 照坤精密儀器大樓 95519",
    "slots": [
      {
        "day": 2,
        "period": "2",
        "type": "講義"
      },
      {
        "day": 2,
        "period": "3",
        "type": "講義"
      },
      {
        "day": 2,
        "period": "4",
        "type": "講義"
      }
    ]
  },
  {
    "id": "P7-073",
    "code": "P7-073 P961400 [IMIS7232E]",
    "name": "智慧型製造系統 人工智慧學分學程 英語授課  製造所、資訊所、AI學位學程、智慧製造學位學程、半導體學院合班，英語授課",
    "grade": 1,
    "credits": 3,
    "required": false,
    "college": "電機資訊學院",
    "departmentCode": "P7",
    "department": "資訊所 CSIE",
    "teacher": "王宏鍇",
    "enrollment": "30/570",
    "locations": [
      "照坤精密儀器大樓",
      "95405"
    ],
    "period": "[1]6~8 照坤精密儀器大樓 95405",
    "slots": [
      {
        "day": 1,
        "period": "6",
        "type": "講義"
      },
      {
        "day": 1,
        "period": "7",
        "type": "講義"
      },
      {
        "day": 1,
        "period": "8",
        "type": "講義"
      }
    ]
  },
  {
    "id": "P7-074",
    "code": "P7-074 P980600 [IMIS7215]",
    "name": "作業研究應用與實作 英語授課 遠距課程  製造所、資訊所合班、遠距線上教學課程、英語授課",
    "grade": 1,
    "credits": 3,
    "required": false,
    "college": "電機資訊學院",
    "departmentCode": "P7",
    "department": "資訊所 CSIE",
    "teacher": "李家岩",
    "enrollment": "11/59",
    "locations": [
      "照坤精密儀器大樓",
      "95509"
    ],
    "period": "[1]2~4 照坤精密儀器大樓 95509",
    "slots": [
      {
        "day": 1,
        "period": "2",
        "type": "講義"
      },
      {
        "day": 1,
        "period": "3",
        "type": "講義"
      },
      {
        "day": 1,
        "period": "4",
        "type": "講義"
      }
    ]
  },
  {
    "id": "P7-075",
    "code": "P7-075 P953500 [IMIS7223]",
    "name": "即時系統 製造所、資訊所合班",
    "grade": 1,
    "credits": 3,
    "required": false,
    "college": "電機資訊學院",
    "departmentCode": "P7",
    "department": "資訊所 CSIE",
    "teacher": "蔡佩璇",
    "enrollment": "22/8",
    "locations": [
      "照坤精密儀器大樓",
      "95519"
    ],
    "period": "[2]5~7 照坤精密儀器大樓 95519",
    "slots": [
      {
        "day": 2,
        "period": "5",
        "type": "講義"
      },
      {
        "day": 2,
        "period": "6",
        "type": "講義"
      },
      {
        "day": 2,
        "period": "7",
        "type": "講義"
      }
    ]
  },
  {
    "id": "P7-078",
    "code": "P7-078 F742900 [CSIE5010]",
    "name": "人工智慧導論 人工智慧學分學程 資訊科學專長微學程  AI聯盟課程，大四碩班合班,資工所醫資所AI學位學程製造所合班，因教室容量限制4264教室採線上同步上課。",
    "grade": 1,
    "credits": 3,
    "required": false,
    "college": "電機資訊學院",
    "departmentCode": "P7",
    "department": "資訊所 CSIE",
    "teacher": "朱威達*",
    "enrollment": "102/28",
    "locations": [
      "資訊系館",
      "4264"
    ],
    "period": "[4]5~7 資訊系館 4264",
    "slots": [
      {
        "day": 4,
        "period": "5",
        "type": "講義"
      },
      {
        "day": 4,
        "period": "6",
        "type": "講義"
      },
      {
        "day": 4,
        "period": "7",
        "type": "講義"
      }
    ]
  },
  {
    "id": "P7-079",
    "code": "P7-079 P75L600 [CSIE7647]",
    "name": "圖機器學習專論 FinTech金融科技學分學程 人工智慧專長微學程  資工所/醫資所/AI學位學程/數據所合班",
    "grade": 1,
    "credits": 3,
    "required": false,
    "college": "電機資訊學院",
    "departmentCode": "P7",
    "department": "資訊所 CSIE",
    "teacher": "李政德",
    "enrollment": "295/26",
    "locations": [
      "65105",
      "資訊新館"
    ],
    "period": "[5]2~4 資訊新館 65105",
    "slots": [
      {
        "day": 5,
        "period": "2",
        "type": "講義"
      },
      {
        "day": 5,
        "period": "3",
        "type": "講義"
      },
      {
        "day": 5,
        "period": "4",
        "type": "講義"
      }
    ]
  },
  {
    "id": "P7-080",
    "code": "P7-080 P75M100 [CSIE7653]",
    "name": "平行與分散式演算法專論 資工所/醫資所/AI學位學程合班",
    "grade": 1,
    "credits": 3,
    "required": false,
    "college": "電機資訊學院",
    "departmentCode": "P7",
    "department": "資訊所 CSIE",
    "teacher": "陳奇業",
    "enrollment": "6/1",
    "locations": [
      "4260",
      "資訊系館"
    ],
    "period": "[3]2~4 資訊系館 4260",
    "slots": [
      {
        "day": 3,
        "period": "2",
        "type": "講義"
      },
      {
        "day": 3,
        "period": "3",
        "type": "講義"
      },
      {
        "day": 3,
        "period": "4",
        "type": "講義"
      }
    ]
  },
  {
    "id": "P7-081",
    "code": "P7-081 P780100 [CSIE7623]",
    "name": "新興記憶體技術導論 資工所/醫資所/AI學位學程/製造所合班",
    "grade": 1,
    "credits": 3,
    "required": false,
    "college": "電機資訊學院",
    "departmentCode": "P7",
    "department": "資訊所 CSIE",
    "teacher": "何建忠",
    "enrollment": "355/5",
    "locations": [
      "資訊系館",
      "4201"
    ],
    "period": "[1]2~4 資訊系館 4201",
    "slots": [
      {
        "day": 1,
        "period": "2",
        "type": "講義"
      },
      {
        "day": 1,
        "period": "3",
        "type": "講義"
      },
      {
        "day": 1,
        "period": "4",
        "type": "講義"
      }
    ]
  },
  {
    "id": "P7-082",
    "code": "P7-082 P773800 [CSIE7630]",
    "name": "無線電接取網路專論 資工所/AI學位學程合班",
    "grade": 1,
    "credits": 3,
    "required": false,
    "college": "電機資訊學院",
    "departmentCode": "P7",
    "department": "資訊所 CSIE",
    "teacher": "曾繁勛",
    "enrollment": "4/532",
    "locations": [
      "4260",
      "資訊系館"
    ],
    "period": "[3]7~9 資訊系館 4260",
    "slots": [
      {
        "day": 3,
        "period": "7",
        "type": "講義"
      },
      {
        "day": 3,
        "period": "8",
        "type": "講義"
      },
      {
        "day": 3,
        "period": "9",
        "type": "講義"
      }
    ]
  },
  {
    "id": "P7-083",
    "code": "P7-083 P773500 [CSIE7627]",
    "name": "升級版第五代行動網路導論 資工所/AI學位學程合班",
    "grade": 1,
    "credits": 3,
    "required": false,
    "college": "電機資訊學院",
    "departmentCode": "P7",
    "department": "資訊所 CSIE",
    "teacher": "曾繁勛",
    "enrollment": "8/258",
    "locations": [
      "4260",
      "資訊系館"
    ],
    "period": "[2]7~9 資訊系館 4260",
    "slots": [
      {
        "day": 2,
        "period": "7",
        "type": "講義"
      },
      {
        "day": 2,
        "period": "8",
        "type": "講義"
      },
      {
        "day": 2,
        "period": "9",
        "type": "講義"
      }
    ]
  },
  {
    "id": "P7-085",
    "code": "P7-085 Q550500 [IMI7650]",
    "name": "神經造影與調控技術 資訊所/醫資所/AI學位學程合班",
    "grade": 1,
    "credits": 3,
    "required": false,
    "college": "電機資訊學院",
    "departmentCode": "P7",
    "department": "資訊所 CSIE",
    "teacher": "詹慧伶",
    "enrollment": "57/53",
    "locations": [
      "資訊系館",
      "4202"
    ],
    "period": "[1]6~8 資訊系館 4202",
    "slots": [
      {
        "day": 1,
        "period": "6",
        "type": "講義"
      },
      {
        "day": 1,
        "period": "7",
        "type": "講義"
      },
      {
        "day": 1,
        "period": "8",
        "type": "講義"
      }
    ]
  },
  {
    "id": "P7-086",
    "code": "P7-086 P954100 [IMIS7215]",
    "name": "智慧製造與決策分析 製造所、資訊所合班",
    "grade": 1,
    "credits": 3,
    "required": false,
    "college": "電機資訊學院",
    "departmentCode": "P7",
    "department": "資訊所 CSIE",
    "teacher": "郭軒安",
    "enrollment": "11/859",
    "locations": [
      "照坤精密儀器大樓",
      "95405"
    ],
    "period": "[4]2~4 照坤精密儀器大樓 95405",
    "slots": [
      {
        "day": 4,
        "period": "2",
        "type": "講義"
      },
      {
        "day": 4,
        "period": "3",
        "type": "講義"
      },
      {
        "day": 4,
        "period": "4",
        "type": "講義"
      }
    ]
  },
  {
    "id": "P7-088",
    "code": "P7-088 P75M500 [CSIE7657]",
    "name": "資料儲存系統導論 資訊所/AI學位學程合班",
    "grade": 1,
    "credits": 3,
    "required": false,
    "college": "電機資訊學院",
    "departmentCode": "P7",
    "department": "資訊所 CSIE",
    "teacher": "謝昀珊",
    "enrollment": "44/11",
    "locations": [
      "65104",
      "資訊新館"
    ],
    "period": "[3]6~8 資訊新館 65104",
    "slots": [
      {
        "day": 3,
        "period": "6",
        "type": "講義"
      },
      {
        "day": 3,
        "period": "7",
        "type": "講義"
      },
      {
        "day": 3,
        "period": "8",
        "type": "講義"
      }
    ]
  },
  {
    "id": "P7-089",
    "code": "P7-089 P75N000 [CSIE7662]",
    "name": "網路安全 資工所/醫資所/AI學位學程合班",
    "grade": 1,
    "credits": 3,
    "required": false,
    "college": "電機資訊學院",
    "departmentCode": "P7",
    "department": "資訊所 CSIE",
    "teacher": "郭紘睿",
    "enrollment": "46/4",
    "locations": [
      "資訊系館",
      "4201"
    ],
    "period": "[3]6~8 資訊系館 4201",
    "slots": [
      {
        "day": 3,
        "period": "6",
        "type": "講義"
      },
      {
        "day": 3,
        "period": "7",
        "type": "講義"
      },
      {
        "day": 3,
        "period": "8",
        "type": "講義"
      }
    ]
  },
  {
    "id": "P7-090",
    "code": "P7-090 NN60800 [ICM5002]",
    "name": "AI圖像識別及機器人實驗室導論 英語授課",
    "grade": 1,
    "credits": 3,
    "required": false,
    "college": "電機資訊學院",
    "departmentCode": "P7",
    "department": "資訊所 CSIE",
    "teacher": "徐禕佑",
    "enrollment": "522/68",
    "locations": [
      "80202",
      "旺宏館"
    ],
    "period": "[3]6~8 旺宏館 80202",
    "slots": [
      {
        "day": 3,
        "period": "6",
        "type": "講義"
      },
      {
        "day": 3,
        "period": "7",
        "type": "講義"
      },
      {
        "day": 3,
        "period": "8",
        "type": "講義"
      }
    ]
  },
  {
    "id": "P7-091",
    "code": "P7-091 P75N100 [CSIE7663]",
    "name": "製造數據與統計推論 資工所/醫資所/AI學位學程/製造所合班",
    "grade": 1,
    "credits": 3,
    "required": false,
    "college": "電機資訊學院",
    "departmentCode": "P7",
    "department": "資訊所 CSIE",
    "teacher": "郭軒安",
    "enrollment": "9/46",
    "locations": [
      "資訊系館",
      "4202"
    ],
    "period": "[3]5~7 資訊系館 4202",
    "slots": [
      {
        "day": 3,
        "period": "5",
        "type": "講義"
      },
      {
        "day": 3,
        "period": "6",
        "type": "講義"
      },
      {
        "day": 3,
        "period": "7",
        "type": "講義"
      }
    ]
  },
  {
    "id": "P7-300",
    "code": "P7-300 P75J510 [CSIE6801]",
    "name": "專題討論（一） 限在職專班選修  限碩專選修",
    "grade": 1,
    "credits": 1,
    "required": true,
    "college": "電機資訊學院",
    "departmentCode": "P7",
    "department": "資訊所 CSIE",
    "teacher": "洪昌鈺",
    "enrollment": "514/1",
    "locations": [
      "65104",
      "資訊新館"
    ],
    "period": "[6]3~4 資訊新館 65104",
    "slots": [
      {
        "day": 6,
        "period": "3",
        "type": "研討"
      },
      {
        "day": 6,
        "period": "4",
        "type": "研討"
      }
    ]
  },
  {
    "id": "P7-302",
    "code": "P7-302 P75J530 [CSIE6803]",
    "name": "專題討論（三） 限在職專班選修，需修習過專題討論(一)(二)  限碩專選修",
    "grade": 1,
    "credits": 1,
    "required": true,
    "college": "電機資訊學院",
    "departmentCode": "P7",
    "department": "資訊所 CSIE",
    "teacher": "洪昌鈺",
    "enrollment": "125/3",
    "locations": [
      "65104",
      "資訊新館"
    ],
    "period": "[6]3~4 資訊新館 65104",
    "slots": [
      {
        "day": 6,
        "period": "3",
        "type": "研討"
      },
      {
        "day": 6,
        "period": "4",
        "type": "研討"
      }
    ]
  },
  {
    "id": "P7-304",
    "code": "P7-304 P75J600 [CSIE6805]",
    "name": "論文研究 限在職專班選修，課程內容依指導教師  限碩專選修",
    "grade": 1,
    "credits": 2,
    "required": true,
    "college": "電機資訊學院",
    "departmentCode": "P7",
    "department": "資訊所 CSIE",
    "teacher": "洪昌鈺",
    "enrollment": "13/2",
    "locations": [
      "65104",
      "資訊新館"
    ],
    "period": "[6]1~2 資訊新館 65104",
    "slots": [
      {
        "day": 6,
        "period": "1",
        "type": "研討"
      },
      {
        "day": 6,
        "period": "2",
        "type": "研討"
      }
    ]
  },
  {
    "id": "P7-306",
    "code": "P7-306 P76I500 [CSIE6807]",
    "name": "數位系統FPGA設計 限在職專班選修  限碩專選修",
    "grade": 1,
    "credits": 3,
    "required": false,
    "college": "電機資訊學院",
    "departmentCode": "P7",
    "department": "資訊所 CSIE",
    "teacher": "陳培殷",
    "enrollment": "15/10",
    "locations": [
      "65203",
      "資訊新館"
    ],
    "period": "[1]A~C 資訊新館 65203",
    "slots": [
      {
        "day": 1,
        "period": "A",
        "type": "講義"
      },
      {
        "day": 1,
        "period": "B",
        "type": "講義"
      },
      {
        "day": 1,
        "period": "C",
        "type": "講義"
      }
    ]
  },
  {
    "id": "P7-312",
    "code": "P7-312 P76I700 [CSIE6813]",
    "name": "Linux 系統與軟體開發 限在職專班選修  限碩專選修",
    "grade": 1,
    "credits": 3,
    "required": false,
    "college": "電機資訊學院",
    "departmentCode": "P7",
    "department": "資訊所 CSIE",
    "teacher": "涂嘉恒",
    "enrollment": "20/10",
    "locations": [
      "65203",
      "資訊新館"
    ],
    "period": "[4]A~C 資訊新館 65203",
    "slots": [
      {
        "day": 4,
        "period": "A",
        "type": "講義"
      },
      {
        "day": 4,
        "period": "B",
        "type": "講義"
      },
      {
        "day": 4,
        "period": "C",
        "type": "講義"
      }
    ]
  },
  {
    "id": "P7-322",
    "code": "P7-322 P76I600-1 [CSIE7617]",
    "name": "深度學習 人工智慧學分學程  限在職專班選修  限碩專選修",
    "grade": 1,
    "credits": 3,
    "required": false,
    "college": "電機資訊學院",
    "departmentCode": "P7",
    "department": "資訊所 CSIE",
    "teacher": "洪昌鈺",
    "enrollment": "18/12",
    "locations": [
      "65104",
      "資訊新館"
    ],
    "period": "[5]A~C 資訊新館 65104",
    "slots": [
      {
        "day": 5,
        "period": "A",
        "type": "講義"
      },
      {
        "day": 5,
        "period": "B",
        "type": "講義"
      },
      {
        "day": 5,
        "period": "C",
        "type": "講義"
      }
    ]
  }
]