[
  {
    "id": "B0-001",
    "code": "B0-001 B011200 [CLA2034]",
    "name": "島嶼之間：臺灣與島嶼東南亞的人群及文化流動 東南亞文化學分學程  彈性密集課程；11月23至24日；地點：振芝講堂",
    "grade": 1,
    "credits": 1,
    "required": false,
    "college": "文學院",
    "departmentCode": "B0",
    "department": "文學院學士班 CLA",
    "teacher": "熊仲卿",
    "enrollment": "18/32",
    "locations": [
      "上課時間"
    ],
    "period": "上課時間",
    "slots": []
  },
  {
    "id": "B0-002",
    "code": "B0-002 B010500 [CLA2025]",
    "name": "水下文化資產政策與法律 考古學與文化資產學分學程",
    "grade": 1,
    "credits": 2,
    "required": false,
    "college": "文學院",
    "departmentCode": "B0",
    "department": "文學院學士班 CLA",
    "teacher": "傅瓊慧",
    "enrollment": "10/20",
    "locations": [
      "考古學研究所",
      "83201"
    ],
    "period": "[5]7~8 考古學研究所 83201",
    "slots": [
      {
        "day": 5,
        "period": "7",
        "type": "講義"
      },
      {
        "day": 5,
        "period": "8",
        "type": "講義"
      }
    ]
  },
  {
    "id": "B0-003",
    "code": "B0-003 B021000 [CLA2021]",
    "name": "旅溯雙城：台南與新竹的自然與人文 彈性密集課程，上課時間 8/25-8/31；0800-2000",
    "grade": 1,
    "credits": 3,
    "required": false,
    "college": "文學院",
    "departmentCode": "B0",
    "department": "文學院學士班 CLA",
    "teacher": "陳文松* 劉家幸 袁彼得",
    "enrollment": "20/額滿",
    "locations": [
      "上課時間"
    ],
    "period": "上課時間",
    "slots": []
  }
]