[
  {
    "id": "K7-001",
    "code": "K7-001 K760600 [Arxe6007]",
    "name": "華南考古學 彈性密集課程",
    "grade": 1,
    "credits": 3,
    "required": false,
    "college": "文學院",
    "departmentCode": "K7",
    "department": "考古所 Arxe",
    "teacher": "熊仲卿*",
    "enrollment": "0/112",
    "locations": [
      "考古學研究所",
      "83102上課時間"
    ],
    "period": "考古學研究所 83102上課時間",
    "slots": []
  },
  {
    "id": "K7-003",
    "code": "K7-003 K767300 [Arxe6087]",
    "name": "研究設計與論文寫作 彈性密集課程",
    "grade": 1,
    "credits": 1,
    "required": true,
    "college": "文學院",
    "departmentCode": "K7",
    "department": "考古所 Arxe",
    "teacher": "趙金勇*",
    "enrollment": "0/115",
    "locations": [
      "考古學研究所",
      "83201上課時間"
    ],
    "period": "考古學研究所 83201上課時間",
    "slots": []
  },
  {
    "id": "K7-004",
    "code": "K7-004 K762901 [Arxe6031]",
    "name": "石器分析 彈性密集課程",
    "grade": 1,
    "credits": 2,
    "required": false,
    "college": "文學院",
    "departmentCode": "K7",
    "department": "考古所 Arxe",
    "teacher": "趙金勇*",
    "enrollment": "0/15",
    "locations": [
      "考古學研究所",
      "83201上課時間"
    ],
    "period": "考古學研究所 83201上課時間",
    "slots": []
  },
  {
    "id": "K7-005",
    "code": "K7-005 K762300 [Arxe6022]",
    "name": "動物考古學 彈性密集課程",
    "grade": 1,
    "credits": 3,
    "required": false,
    "college": "文學院",
    "departmentCode": "K7",
    "department": "考古所 Arxe",
    "teacher": "閻玲達*",
    "enrollment": "0/10",
    "locations": [
      "考古學研究所",
      "83201上課時間"
    ],
    "period": "考古學研究所 83201上課時間",
    "slots": []
  },
  {
    "id": "K7-006",
    "code": "K7-006 K763400 [Arxe6039]",
    "name": "田野考古學（一）：調查與發掘方法 彈性密集課程",
    "grade": 1,
    "credits": 2,
    "required": true,
    "college": "文學院",
    "departmentCode": "K7",
    "department": "考古所 Arxe",
    "teacher": "鍾國風*",
    "enrollment": "0/12",
    "locations": [
      "考古學研究所",
      "83102上課時間"
    ],
    "period": "考古學研究所 83102上課時間",
    "slots": []
  },
  {
    "id": "K7-007",
    "code": "K7-007 K770100 [Arxe9001]",
    "name": "進階考古學田野方法 彈性密集課程",
    "grade": 1,
    "credits": 2,
    "required": true,
    "college": "文學院",
    "departmentCode": "K7",
    "department": "考古所 Arxe",
    "teacher": "鍾國風*",
    "enrollment": "10/3",
    "locations": [
      "考古學研究所",
      "83102上課時間"
    ],
    "period": "考古學研究所 83102上課時間",
    "slots": []
  },
  {
    "id": "K7-008",
    "code": "K7-008 K764900 [Arxe6053]",
    "name": "考古材料學之科學分析 考古學與文化資產學分學程  彈性密集課程(1150801新聘教師陳鴻文)",
    "grade": 1,
    "credits": 3,
    "required": false,
    "college": "文學院",
    "departmentCode": "K7",
    "department": "考古所 Arxe",
    "teacher": "",
    "enrollment": "0/115",
    "locations": [
      "考古學研究所",
      "83201上課時間"
    ],
    "period": "考古學研究所 83201上課時間",
    "slots": []
  },
  {
    "id": "K7-009",
    "code": "K7-009 K766700 [Arxe6072]",
    "name": "南島文化與研究 考古學與文化資產學分學程  彈性密集課程",
    "grade": 1,
    "credits": 3,
    "required": false,
    "college": "文學院",
    "departmentCode": "K7",
    "department": "考古所 Arxe",
    "teacher": "台邦．撒沙勒*",
    "enrollment": "10/12",
    "locations": [
      "考古學研究所",
      "83102上課時間"
    ],
    "period": "考古學研究所 83102上課時間",
    "slots": []
  },
  {
    "id": "K7-010",
    "code": "K7-010 K751000 [Arxe6081]",
    "name": "考古學與博物館 考古學與文化資產學分學程  彈性密集課程",
    "grade": 1,
    "credits": 2,
    "required": false,
    "college": "文學院",
    "departmentCode": "K7",
    "department": "考古所 Arxe",
    "teacher": "閻玲達*",
    "enrollment": "10/6",
    "locations": [
      "考古學研究所",
      "83102上課時間"
    ],
    "period": "考古學研究所 83102上課時間",
    "slots": []
  },
  {
    "id": "K7-011",
    "code": "K7-011 K761402 [Arxe6088]",
    "name": "臺灣考古學專題討論 彈性密集課程",
    "grade": 1,
    "credits": 2,
    "required": true,
    "college": "文學院",
    "departmentCode": "K7",
    "department": "考古所 Arxe",
    "teacher": "趙金勇* 鍾國風 熊仲卿 閻玲達",
    "enrollment": "0/115",
    "locations": [
      "考古學研究所",
      "83201上課時間"
    ],
    "period": "考古學研究所 83201上課時間",
    "slots": []
  },
  {
    "id": "K7-012",
    "code": "K7-012 K750800 [Arxe6081]",
    "name": "考古學概論經典導讀 彈性密集課程",
    "grade": 1,
    "credits": 1,
    "required": false,
    "college": "文學院",
    "departmentCode": "K7",
    "department": "考古所 Arxe",
    "teacher": "趙金勇* 鍾國風 熊仲卿 閻玲達",
    "enrollment": "0/12",
    "locations": [
      "考古學研究所",
      "83102上課時間"
    ],
    "period": "考古學研究所 83102上課時間",
    "slots": []
  },
  {
    "id": "K7-013",
    "code": "K7-013 K766800 [Arxe6073]",
    "name": "原住民族聚落與文化資產保存 考古學與文化資產學分學程 原住民族文化暨社會實踐專長微學程  彈性密集課程。本課程連續安排6日校外教學(115/12/31-116/01/05)，且包含國定假日，學生請謹慎評估後再選課。",
    "grade": 1,
    "credits": 3,
    "required": false,
    "college": "文學院",
    "departmentCode": "K7",
    "department": "考古所 Arxe",
    "teacher": "台邦．撒沙勒*",
    "enrollment": "0/5",
    "locations": [
      "考古學研究所",
      "83102上課時間"
    ],
    "period": "考古學研究所 83102上課時間",
    "slots": []
  }
]