[
  {
    "id": "K3-100",
    "code": "K3-100 K354811 [HIS6105]",
    "name": "論文寫作與實習（一） 基礎課程，碩士班必修",
    "grade": 1,
    "credits": 2,
    "required": true,
    "college": "文學院",
    "departmentCode": "K3",
    "department": "歷史所 HIS",
    "teacher": "謝美娥",
    "enrollment": "0/20",
    "locations": [
      "25234",
      "歷史系館"
    ],
    "period": "[2]3~4 歷史系館 25234",
    "slots": [
      {
        "day": 2,
        "period": "3",
        "type": "講義"
      },
      {
        "day": 2,
        "period": "4",
        "type": "講義"
      }
    ]
  },
  {
    "id": "K3-102",
    "code": "K3-102 K354410 [HIS6101]",
    "name": "專業史學日文（一） 碩士班高級史學英文、專業史學日文擇一必修",
    "grade": 1,
    "credits": 0,
    "required": true,
    "college": "文學院",
    "departmentCode": "K3",
    "department": "歷史所 HIS",
    "teacher": "李啟彰",
    "enrollment": "0/112",
    "locations": [
      "25232",
      "歷史系館"
    ],
    "period": "[5]2~4 歷史系館 25232",
    "slots": [
      {
        "day": 5,
        "period": "2",
        "type": "講義"
      },
      {
        "day": 5,
        "period": "3",
        "type": "講義"
      },
      {
        "day": 5,
        "period": "4",
        "type": "講義"
      }
    ]
  },
  {
    "id": "K3-103",
    "code": "K3-103 K354310 [HIS6103]",
    "name": "高級史學英文（一） 英語授課  碩士班高級史學英文、專業史學日文擇一必修",
    "grade": 1,
    "credits": 0,
    "required": true,
    "college": "文學院",
    "departmentCode": "K3",
    "department": "歷史所 HIS",
    "teacher": "徐維里",
    "enrollment": "01/12",
    "locations": [
      "25234",
      "歷史系館"
    ],
    "period": "[5]2~4 歷史系館 25234",
    "slots": [
      {
        "day": 5,
        "period": "2",
        "type": "講義"
      },
      {
        "day": 5,
        "period": "3",
        "type": "講義"
      },
      {
        "day": 5,
        "period": "4",
        "type": "講義"
      }
    ]
  },
  {
    "id": "K3-115",
    "code": "K3-115 K38F000 [HIS7116]",
    "name": "近代初期臺灣史料選讀",
    "grade": 1,
    "credits": 3,
    "required": false,
    "college": "文學院",
    "departmentCode": "K3",
    "department": "歷史所 HIS",
    "teacher": "簡宏逸",
    "enrollment": "0/10",
    "locations": [
      "25233",
      "歷史系館"
    ],
    "period": "[2]2~4 歷史系館 25233",
    "slots": [
      {
        "day": 2,
        "period": "2",
        "type": "講義"
      },
      {
        "day": 2,
        "period": "3",
        "type": "講義"
      },
      {
        "day": 2,
        "period": "4",
        "type": "講義"
      }
    ]
  },
  {
    "id": "K3-128",
    "code": "K3-128 K383600 [HIS7131]",
    "name": "愛爾蘭史專題研究",
    "grade": 1,
    "credits": 3,
    "required": false,
    "college": "文學院",
    "departmentCode": "K3",
    "department": "歷史所 HIS",
    "teacher": "張勝柏",
    "enrollment": "0/112",
    "locations": [
      "25131",
      "歷史系館"
    ],
    "period": "[4]2~4 歷史系館 25131",
    "slots": [
      {
        "day": 4,
        "period": "2",
        "type": "講義"
      },
      {
        "day": 4,
        "period": "3",
        "type": "講義"
      },
      {
        "day": 4,
        "period": "4",
        "type": "講義"
      }
    ]
  },
  {
    "id": "K3-129",
    "code": "K3-129 K38F100 [HIS7117]",
    "name": "動物史學專題",
    "grade": 1,
    "credits": 3,
    "required": false,
    "college": "文學院",
    "departmentCode": "K3",
    "department": "歷史所 HIS",
    "teacher": "李鑑慧",
    "enrollment": "01/12",
    "locations": [
      "25233",
      "歷史系館"
    ],
    "period": "[2]6~8 歷史系館 25233",
    "slots": [
      {
        "day": 2,
        "period": "6",
        "type": "講義"
      },
      {
        "day": 2,
        "period": "7",
        "type": "講義"
      },
      {
        "day": 2,
        "period": "8",
        "type": "講義"
      }
    ]
  },
  {
    "id": "K3-140",
    "code": "K3-140 K38D500 [HIS7115]",
    "name": "殖民邊緣史",
    "grade": 1,
    "credits": 3,
    "required": false,
    "college": "文學院",
    "departmentCode": "K3",
    "department": "歷史所 HIS",
    "teacher": "梁秋虹",
    "enrollment": "0/10",
    "locations": [
      "25231",
      "歷史系館"
    ],
    "period": "[1]6~8 歷史系館 25231",
    "slots": [
      {
        "day": 1,
        "period": "6",
        "type": "講義"
      },
      {
        "day": 1,
        "period": "7",
        "type": "講義"
      },
      {
        "day": 1,
        "period": "8",
        "type": "講義"
      }
    ]
  },
  {
    "id": "K3-141",
    "code": "K3-141 K38B900 [HIS7128]",
    "name": "臺灣物質文化史專題研究",
    "grade": 1,
    "credits": 3,
    "required": false,
    "college": "文學院",
    "departmentCode": "K3",
    "department": "歷史所 HIS",
    "teacher": "謝仕淵",
    "enrollment": "0/10",
    "locations": [
      "25240",
      "歷史系館"
    ],
    "period": "[5]6~8 歷史系館 25240",
    "slots": [
      {
        "day": 5,
        "period": "6",
        "type": "講義"
      },
      {
        "day": 5,
        "period": "7",
        "type": "講義"
      },
      {
        "day": 5,
        "period": "8",
        "type": "講義"
      }
    ]
  },
  {
    "id": "K3-150",
    "code": "K3-150 K38B000 [HIS7112]",
    "name": "歐洲帝國勢力、美國、日本之東南亞殖民史 東南亞文化學分學程 英語授課",
    "grade": 1,
    "credits": 2,
    "required": false,
    "college": "文學院",
    "departmentCode": "K3",
    "department": "歷史所 HIS",
    "teacher": "董梵",
    "enrollment": "0/12",
    "locations": [
      "25231",
      "歷史系館"
    ],
    "period": "[5]6~7 歷史系館 25231",
    "slots": [
      {
        "day": 5,
        "period": "6",
        "type": "講義"
      },
      {
        "day": 5,
        "period": "7",
        "type": "講義"
      }
    ]
  },
  {
    "id": "K3-151",
    "code": "K3-151 K381800 [HIS7041]",
    "name": "明代佛教與社會專題",
    "grade": 1,
    "credits": 3,
    "required": false,
    "college": "文學院",
    "departmentCode": "K3",
    "department": "歷史所 HIS",
    "teacher": "陳玉女",
    "enrollment": "01/10",
    "locations": [
      "25240",
      "歷史系館"
    ],
    "period": "[2]2~4 歷史系館 25240",
    "slots": [
      {
        "day": 2,
        "period": "2",
        "type": "講義"
      },
      {
        "day": 2,
        "period": "3",
        "type": "講義"
      },
      {
        "day": 2,
        "period": "4",
        "type": "講義"
      }
    ]
  },
  {
    "id": "K3-160",
    "code": "K3-160 K360201 [HIS7221]",
    "name": "獨立研究 供碩三博三以上同學選課，由指導教授授課",
    "grade": 1,
    "credits": 0,
    "required": true,
    "college": "文學院",
    "departmentCode": "K3",
    "department": "歷史所 HIS",
    "teacher": "許守泯",
    "enrollment": "0/100",
    "locations": [
      "未定"
    ],
    "period": "未定",
    "slots": []
  },
  {
    "id": "K3-250",
    "code": "K3-250 K375210 [HIS7223]",
    "name": "史學與史學研究（一） 基礎課程。博士班必修",
    "grade": 1,
    "credits": 2,
    "required": true,
    "college": "文學院",
    "departmentCode": "K3",
    "department": "歷史所 HIS",
    "teacher": "陳恒安",
    "enrollment": "10/10",
    "locations": [
      "25232",
      "歷史系館"
    ],
    "period": "[1]2~3 歷史系館 25232",
    "slots": [
      {
        "day": 1,
        "period": "2",
        "type": "講義"
      },
      {
        "day": 1,
        "period": "3",
        "type": "講義"
      }
    ]
  },
  {
    "id": "K3-260",
    "code": "K3-260 K387800 [HIS7170]",
    "name": "台灣政治文化史專題 開放碩班修課",
    "grade": 1,
    "credits": 3,
    "required": false,
    "college": "文學院",
    "departmentCode": "K3",
    "department": "歷史所 HIS",
    "teacher": "陳文松",
    "enrollment": "0/10",
    "locations": [
      "25240",
      "歷史系館"
    ],
    "period": "[4]6~8 歷史系館 25240",
    "slots": [
      {
        "day": 4,
        "period": "6",
        "type": "講義"
      },
      {
        "day": 4,
        "period": "7",
        "type": "講義"
      },
      {
        "day": 4,
        "period": "8",
        "type": "講義"
      }
    ]
  },
  {
    "id": "K3-261",
    "code": "K3-261 K389000 [HIS7150]",
    "name": "生育禮俗專題研究 開放碩班修課。",
    "grade": 1,
    "credits": 2,
    "required": false,
    "college": "文學院",
    "departmentCode": "K3",
    "department": "歷史所 HIS",
    "teacher": "江達智",
    "enrollment": "0/12",
    "locations": [
      "25234",
      "歷史系館"
    ],
    "period": "[4]3~4 歷史系館 25234",
    "slots": [
      {
        "day": 4,
        "period": "3",
        "type": "講義"
      },
      {
        "day": 4,
        "period": "4",
        "type": "講義"
      }
    ]
  },
  {
    "id": "K3-262",
    "code": "K3-262 K387700 [HIS7111]",
    "name": "近代臺灣海關史專題研究 開放碩班修課",
    "grade": 1,
    "credits": 3,
    "required": false,
    "college": "文學院",
    "departmentCode": "K3",
    "department": "歷史所 HIS",
    "teacher": "陳計堯",
    "enrollment": "10/6",
    "locations": [
      "25231",
      "歷史系館"
    ],
    "period": "[2]6~8 歷史系館 25231",
    "slots": [
      {
        "day": 2,
        "period": "6",
        "type": "講義"
      },
      {
        "day": 2,
        "period": "7",
        "type": "講義"
      },
      {
        "day": 2,
        "period": "8",
        "type": "講義"
      }
    ]
  }
]